genshi/__init__.py
genshi/_speedups.c
genshi/builder.py
genshi/compat.py
genshi/core.py
genshi/input.py
genshi/output.py
genshi/path.py
genshi/util.py
genshi/filters/__init__.py
genshi/filters/html.py
genshi/filters/i18n.py
genshi/filters/transform.py
genshi/filters/tests/__init__.py
genshi/filters/tests/i18n.py
genshi/filters/tests/test_html.py
genshi/filters/tests/transform.py
genshi/template/__init__.py
genshi/template/astutil.py
genshi/template/base.py
genshi/template/directives.py
genshi/template/eval.py
genshi/template/interpolation.py
genshi/template/loader.py
genshi/template/markup.py
genshi/template/plugin.py
genshi/template/text.py
genshi/template/tests/__init__.py
genshi/template/tests/base.py
genshi/template/tests/directives.py
genshi/template/tests/eval.py
genshi/template/tests/interpolation.py
genshi/template/tests/loader.py
genshi/template/tests/markup.py
genshi/template/tests/plugin.py
genshi/template/tests/text.py
genshi/template/tests/templates/__init__.py
genshi/template/tests/templates/functions.html
genshi/template/tests/templates/functions.txt
genshi/template/tests/templates/new_syntax.txt
genshi/template/tests/templates/test.html
genshi/template/tests/templates/test.txt
genshi/template/tests/templates/test_no_doctype.html
genshi/tests/__init__.py
genshi/tests/builder.py
genshi/tests/core.py
genshi/tests/input.py
genshi/tests/output.py
genshi/tests/path.py
genshi/tests/test_utils.py
genshi/tests/util.py
Genshi-0.7.9.dist-info/COPYING
Genshi-0.7.9.dist-info/METADATA
Genshi-0.7.9.dist-info/WHEEL
Genshi-0.7.9.dist-info/entry_points.txt
Genshi-0.7.9.dist-info/top_level.txt
Genshi-0.7.9.dist-info/RECORD
